pyams_fields/__init__.py
pyams_fields/captcha.py
pyams_fields/container.py
pyams_fields/field.py
pyams_fields/handler.py
pyams_fields/include.py
pyams_fields/interfaces.py
pyams_fields/rgpd.py
pyams_fields/doctests/README.rst
pyams_fields/locales/pyams_fields.pot
pyams_fields/locales/fr/LC_MESSAGES/pyams_fields.mo
pyams_fields/locales/fr/LC_MESSAGES/pyams_fields.po
pyams_fields/skin/__init__.py
pyams_fields/skin/captcha.py
pyams_fields/skin/converter.py
pyams_fields/skin/interfaces.py
pyams_fields/skin/rgpd.py
pyams_fields/skin/templates/recaptcha.pt
pyams_fields/skin/templates/rgpd-consent-widget.pt
pyams_fields/tests/__init__.py
pyams_fields/tests/test_utilsdocs.py
pyams_fields/tests/test_utilsdocstrings.py
pyams_fields/zmi/__init__.py
pyams_fields/zmi/captcha.py
pyams_fields/zmi/container.py
pyams_fields/zmi/handler.py
pyams_fields/zmi/interfaces.py
pyams_fields/zmi/rgpd.py
pyams_fields/zmi/templates/rgpd-user-rights.pt
pyams_fields/zmi/templates/rgpd-warning.pt
pyams_fields-2.0.1.dist-info/LICENSE
pyams_fields-2.0.1.dist-info/METADATA
pyams_fields-2.0.1.dist-info/WHEEL
pyams_fields-2.0.1.dist-info/namespace_packages.txt
pyams_fields-2.0.1.dist-info/top_level.txt
pyams_fields-2.0.1.dist-info/RECORD
