Metadata-Version: 2.1
Name: pyams-fields
Version: 2.0.1
Summary: PyAMS custom form fields management
Home-page: https://pyams.readthedocs.io
Author: Thierry Florac
Author-email: tflorac@ulthar.net
License: ZPL
Keywords: Pyramid PyAMS
Classifier: License :: OSI Approved :: Zope Public License
Classifier: Development Status :: 4 - Beta
Classifier: Programming Language :: Python
Classifier: Framework :: Pyramid
Classifier: Topic :: Software Development :: Libraries :: Python Modules
License-File: LICENSE
Requires-Dist: setuptools
Requires-Dist: persistent
Requires-Dist: pyams-i18n
Requires-Dist: pyams-pagelet
Requires-Dist: pyams-portal
Requires-Dist: pyams-security
Requires-Dist: pyams-skin
Requires-Dist: pyams-template
Requires-Dist: pyams-utils
Requires-Dist: pyams-viewlet
Requires-Dist: pyramid >=2.0.0
Requires-Dist: requests
Requires-Dist: zope.annotation
Requires-Dist: zope.componentvocabulary
Requires-Dist: zope.container
Requires-Dist: zope.copy
Requires-Dist: zope.interface
Requires-Dist: zope.location
Requires-Dist: zope.schema
Requires-Dist: zope.traversing
Provides-Extra: test
Requires-Dist: pyams-zmi ; extra == 'test'
Requires-Dist: pyramid-zcml ; extra == 'test'
Requires-Dist: zope.exceptions ; extra == 'test'
